pytest_kafka/__init__.py
pytest_kafka/_factories.py
pytest_kafka/_fixtures.py
pytest_kafka/constants.py
pytest_kafka/install.py
pytest_kafka/py.typed
pytest_kafka-0.8.1.dist-info/LICENCE
pytest_kafka-0.8.1.dist-info/METADATA
pytest_kafka-0.8.1.dist-info/WHEEL
pytest_kafka-0.8.1.dist-info/entry_points.txt
pytest_kafka-0.8.1.dist-info/top_level.txt
pytest_kafka-0.8.1.dist-info/RECORD
