Metadata-Version: 2.1
Name: pytest-kafka
Version: 0.8.1
Summary: Zookeeper, Kafka server, and Kafka consumer fixtures for Pytest
Home-page: https://gitlab.com/karolinepauls/pytest-kafka
Author: Karoline Pauls
Author-email: code@karolinepauls.com
License: MIT
Project-URL: Bug Tracker, https://gitlab.com/karolinepauls/pytest-kafka/issues
Project-URL: Documentation, https://pytest-kafka.readthedocs.io/
Project-URL: Source Code, https://gitlab.com/karolinepauls/pytest-kafka
Classifier: Framework :: Pytest
Classifier: Topic :: Software Development :: Testing
Classifier: License :: OSI Approved :: BSD License
Classifier: Programming Language :: Python :: 3.6
Classifier: Programming Language :: Python :: 3.7
Classifier: Programming Language :: Python :: 3.8
Classifier: Programming Language :: Python :: 3.9
License-File: LICENCE
Requires-Dist: pytest
Requires-Dist: port-for>=0.4
Provides-Extra: dev
Requires-Dist: flake8; extra == "dev"
Requires-Dist: pyflakes>=1.6.0; extra == "dev"
Requires-Dist: flake8-docstrings; extra == "dev"
Requires-Dist: flake8-tuple; extra == "dev"
Requires-Dist: mypy; extra == "dev"
Provides-Extra: doc
Requires-Dist: Sphinx==7.4.7; extra == "doc"
Requires-Dist: sphinx-rtd-theme==2.0.0; extra == "doc"
Provides-Extra: kafka-python
Requires-Dist: kafka-python>=1.4.3; extra == "kafka-python"
Provides-Extra: kafka-python-ng
Requires-Dist: kafka-python-ng>=2.2.2; extra == "kafka-python-ng"
